djangoldp_ontochain/__init__.py
djangoldp_ontochain/admin.py
djangoldp_ontochain/apps.py
djangoldp_ontochain/factories.py
djangoldp_ontochain/models.py
djangoldp_ontochain/settings.py
djangoldp_ontochain/management/__init__.py
djangoldp_ontochain/management/commands/__init__.py
djangoldp_ontochain/management/commands/mock_example.py
djangoldp_ontochain/migrations/0001_initial.py
djangoldp_ontochain/migrations/0002_auto_20230419_1745.py
djangoldp_ontochain/migrations/__init__.py
djangoldp_ontochain-1.0.0.dist-info/METADATA
djangoldp_ontochain-1.0.0.dist-info/WHEEL
djangoldp_ontochain-1.0.0.dist-info/top_level.txt
djangoldp_ontochain-1.0.0.dist-info/RECORD
