Metadata-Version: 2.1
Name: djangoldp-ontochain
Version: 1.0.0
Summary: djangoldp ontochain package
Home-page: http://git.happy-dev.fr/startinblox/djangoldp_ontochain
Author: Startin'blox
Author-email: contact@startinblox.com
License: MIT
Requires-Dist: djangoldp (~=3.0)
Requires-Dist: djangoldp-account (~=3.0)
Provides-Extra: dev
Requires-Dist: factory-boy (>=2.11.0) ; extra == 'dev'
